gradio_awsbr_mmchatbot/__init__.py
gradio_awsbr_mmchatbot/multimodalchatbot.py
gradio_awsbr_mmchatbot/multimodalchatbot.pyi
gradio_awsbr_mmchatbot/templates/component/index.js
gradio_awsbr_mmchatbot/templates/component/style.css
gradio_awsbr_mmchatbot/templates/component/assets/worker-43d19264.js
gradio_awsbr_mmchatbot-0.0.5.dist-info/METADATA
gradio_awsbr_mmchatbot-0.0.5.dist-info/WHEEL
gradio_awsbr_mmchatbot-0.0.5.dist-info/RECORD
