Metadata-Version: 2.3
Name: gradio_awsbr_mmchatbot
Version: 0.0.5
Summary: This component enables multi-modal input for the Anthropic Claude v3 suite of models available from Amazon Bedrock
Author: Jedijamez
License-Expression: MIT
Keywords: AWS,Amazon Bedrock,Anthropic,Bedrock,Chatbot,Claude,Claude v3,LLM,Multimodal,gradio-custom-component,gradio-template-Chatbot
Classifier: Development Status :: 3 - Alpha
Classifier: License :: OSI Approved :: Apache Software License
Classifier: Operating System :: OS Independent
Classifier: Programming Language :: Python :: 3
Classifier: Programming Language :: Python :: 3 :: Only
Classifier: Programming Language :: Python :: 3.8
Classifier: Programming Language :: Python :: 3.9
Classifier: Programming Language :: Python :: 3.10
Classifier: Programming Language :: Python :: 3.11
Classifier: Topic :: Scientific/Engineering
Classifier: Topic :: Scientific/Engineering :: Artificial Intelligence
Classifier: Topic :: Scientific/Engineering :: Visualization
Requires-Python: >=3.8
Requires-Dist: gradio<5.0,>=4.0
Provides-Extra: dev
Requires-Dist: build; extra == 'dev'
Requires-Dist: twine; extra == 'dev'
